sermain.cpython-312-x86_64-linux-gnu.so
sermain/__init__.py
sermain/sermain.cpython-312-x86_64-linux-gnu.so
sermain-0.1.0.dist-info/METADATA
sermain-0.1.0.dist-info/WHEEL
sermain-0.1.0.dist-info/top_level.txt
sermain-0.1.0.dist-info/RECORD
sermain-0.1.0.dist-info/licenses/LICENSE
