Metadata-Version: 2.4
Name: sermain
Version: 0.1.0
Summary: My Python extension module
Author-email: Your Name <you@example.com>
License: MIT
Requires-Python: >=3.8
License-File: LICENSE
Dynamic: license-file
